{
  "source": "https://sites.google.com/view/dtnlab",
  "recruitment": {
    "intro": "DTPLab에서는 Digital Twin, Physical AI, Robotics 및 AI 최적화 분야의 연구를 함께 수행할 대학원생과 학부연구생을 모집합니다.",
    "sections": [
      {"title": "수행 연구", "items": ["Digital Twin 시뮬레이션과 Sim2Real 전이학습", "Physical AI 및 로봇 지능", "Deep Surrogate Modeling", "강화학습·베이지안 최적화 기반 산업 최적화"]},
      {"title": "모집 대상", "items": ["컴퓨터공학·인공지능 및 관련 전공 대학원 진학 희망자", "Digital Twin과 Physical AI 연구에 관심 있는 학생", "자기주도적으로 연구를 수행할 수 있는 학생"]},
      {"title": "지원 방법", "items": ["성적증명서와 자유양식 연구계획서를 이메일로 제출", "연구실 T/O 확인", "대면 또는 온라인 면담 후 합류 결정"]},
      {"title": "지원 내역", "items": ["연구과제 참여에 따른 연구비 지원", "국내외 학술대회 발표 및 연구 활동 지원", "개인 연구공간과 연구장비 제공"]},
      {"title": "연락처", "items": ["wonsukkim@pusan.ac.kr", "부산대학교 IT관 610호"]}
    ]
  }
}
